{
    "Types": "Types",
    "java.util.concurrent.ConcurrentMap<Class<?>,TypedStringConverter<?>>": "",
    "long": "",
    "java.lang.reflect.TypeVariable<>": "",
    "StringConverterFactory": "StringConverterFactory",
    "java.lang.Class<? extends Type>": "",
    "HasCodeImpl": "HasCodeImpl",
    "java.util.concurrent.CopyOnWriteArrayList<StringConverterFactory>": "",
    "RenameHandler": "RenameHandler",
    "TypeVariableImpl<D>": "",
    "java.net.MalformedURLException": "",
    "TypeToken<>": "",
    "int": "",
    "JavaVersion": "JavaVersion",
    "DistanceMethodAndConstructorAnnotations": "DistanceMethodAndConstructorAnnotations",
    "byte[]": "",
    "java.io.Serializable": "",
    "java.util.concurrent.atomic.AtomicLong": "",
    "java.security.AccessControlException": "",
    "java.lang.ClassNotFoundException": "",
    "CharecterArrayStringConverter": "CharecterArrayStringConverter",
    "java.lang.Class<? extends Boolean[]>": "",
    "DistanceFromStringConstructorInvalidParameterCount": "DistanceFromStringConstructorInvalidParameterCount",
    "TestBooleanArrayStringConverterFactory": "TestBooleanArrayStringConverterFactory",
    "java.util.List<? extends Number>": "",
    "Test3Class": "Test3Class",
    "java.lang.StringBuffer": "",
    "java.lang.Double[]": "",
    "CharObjectArrayStringConverterFactory": "CharObjectArrayStringConverterFactory",
    "TypedFromStringConverter": "TypedFromStringConverter",
    "TypeToken<List<? extends Number>>": "",
    "TypedStringConverter<boolean[]>": "",
    "OptionalDoubleStringConverter": "OptionalDoubleStringConverter",
    "TypedStringConverter<short[]>": "",
    "double": "",
    "boolean": "",
    "TypedStringConverter<DistanceMethodMethodCharSequence>": "",
    "FromString": "",
    "java.lang.ClassLoader": "",
    "TypedAdapter<R>": "",
    "TypeToken<Map<String,List<Integer>>>": "",
    "TypedStringConverter<>": "",
    "Factory1": "Factory1",
    "SubNoAnnotations": "SubNoAnnotations",
    "java.lang.Class<? extends Enum<>>": "",
    "java.util.SimpleTimeZone": "",
    "java.lang.RuntimeException": "",
    "ByteArrayStringConverter": "ByteArrayStringConverter",
    "AltCharSequence": "AltCharSequence",
    "java.lang.IllegalStateException": "",
    "java.lang.InstantiationException": "",
    "StringConverter<T>": "",
    "java.util.Map<? extends CharSequence,? extends Number>": "",
    "TypeToken<List<String>>": "",
    "java.lang.Class<? extends Short[]>": "",
    "TypeToken<List<?>>": "",
    "java.util.Map<String,Map<Integer,Double>>": "",
    "TypeUtils": "TypeUtils",
    "java.lang.reflect.InvocationTargetException": "",
    "TypedStringConverter<Long[]>": "",
    "R": "",
    "TypeVariableImpl<?>": "",
    "java.util.Locale": "",
    "java.lang.Enum<T>": "",
    "TypeCapture<Entry<String,int[][]>>": "",
    "java.util.List<Integer>": "",
    "TypedStringConverter<Object>": "",
    "java.io.BufferedReader": "",
    "Test4Class": "Test4Class",
    "Test4Interface": "Test4Interface",
    "TypedStringConverter<Integer[]>": "",
    "short[]": "",
    "java.util.Map<String,Enum<?>>": "",
    "BooleanObjectArrayStringConverterFactory": "BooleanObjectArrayStringConverterFactory",
    "DistanceTwoToStringAnnotations": "DistanceTwoToStringAnnotations",
    "java.lang.CharSequence": "",
    "TypeToken<List<? super Integer>>": "",
    "TestCharObjectArrayStringConverterFactory": "TestCharObjectArrayStringConverterFactory",
    "java.lang.reflect.TypeVariable<D>": "",
    "float[]": "",
    "TypedStringConverter<Status>": "",
    "ToString": "",
    "java.lang.Float": "",
    "double[]": "",
    "ReflectionStringConverter": "ReflectionStringConverter",
    "D": "",
    "StringConvert": "StringConvert",
    "java.lang.Short": "",
    "ShortArrayStringConverter": "ShortArrayStringConverter",
    "TypeToken<?>": "",
    "java.lang.Float[]": "",
    "java.util.ArrayList<String>": "",
    "TypedStringConverter<Boolean[]>": "",
    "java.lang.Class<? extends Byte[]>": "",
    "java.lang.Class<Integer>": "",
    "DistanceNoAnnotations": "DistanceNoAnnotations",
    "FromStringConverter<T>": "",
    "java.lang.Character": "",
    "TypedStringConverter<int[]>": "",
    "DistanceMethodMethod": "DistanceMethodMethod",
    "FromStringFactory": "FromStringFactory",
    "java.util.Date": "",
    "java.util.TimeZone": "",
    "Test2Class": "Test2Class",
    "Test2Interface": "Test2Interface",
    "OptionalIntStringConverter": "OptionalIntStringConverter",
    "NativeTypeVariableEquals<>": "",
    "java.lang.Integer[]": "",
    "java.lang.Class<?>": "",
    "java.lang.Class<? extends Float[]>": "",
    "java.util.concurrent.atomic.AtomicReference<Type>": "",
    "java.lang.AssertionError": "",
    "java.lang.Byte": "",
    "java.lang.reflect.WildcardType": "",
    "MethodFromStringConverter": "MethodFromStringConverter",
    "StringConverter<DistanceToStringException>": "",
    "java.lang.reflect.Type[]": "",
    "ConstructorFromStringConverter<>": "",
    "WildcardTypeImpl": "WildcardTypeImpl",
    "java.lang.reflect.GenericDeclaration": "",
    "java.util.ArrayList<Type>": "",
    "java.util.Collection<Type>": "",
    "DistanceToStringException": "DistanceToStringException",
    "TypedStringConverter<double[]>": "",
    "java.io.ByteArrayOutputStream": "",
    "DistanceFromStringConstructorInvalidParameter": "DistanceFromStringConstructorInvalidParameter",
    "java.io.InputStreamReader": "",
    "java.math.BigDecimal": "",
    "java.lang.NoSuchMethodException": "",
    "TypeVisitor": "TypeVisitor",
    "boolean[]": "",
    "JDKStringConverter": "JDKStringConverter",
    "java.util.concurrent.ConcurrentMap<Class<?>,FromStringConverter<?>>": "",
    "TypeVariableImpl<>": "",
    "DistanceMethodMethodCharSequence": "DistanceMethodMethodCharSequence",
    "java.lang.Class<R>": "",
    "TypeToken<Map<? extends CharSequence,? extends Number>>": "",
    "TypeStringConverter": "TypeStringConverter",
    "MethodFromStringConverter<T>": "",
    "java.util.concurrent.ConcurrentHashMap<Class<?>,Map<String,Enum<?>>>": "",
    "TypeToken<List<String[]>>": "",
    "java.util.Set<Type>": "",
    "java.lang.StringBuilder": "",
    "java.lang.Class<>": "",
    "java.lang.Class<? extends Long[]>": "",
    "java.util.Set<Class<?>>": "",
    "java.util.List<?>": "",
    "TypeStringConverterFactory": "TypeStringConverterFactory",
    "java.util.Map<String,Integer>": "",
    "BooleanArrayStringConverterFactory": "BooleanArrayStringConverterFactory",
    "float": "",
    "TypedStringConverter<SubMethodConstructor>": "",
    "java.lang.reflect.InvocationHandler": "",
    "TypedStringConverter<Byte[]>": "",
    "java.lang.Class<? extends Enum<?>>": "",
    "TypedStringConverter<float[]>": "",
    "ValidityStringConverter": "ValidityStringConverter",
    "java.net.URL": "",
    "Test1Class": "Test1Class",
    "java.lang.Class<? extends Integer>": "",
    "TypeToken<Map<String,? extends List<? extends Integer>>>": "",
    "java.lang.Class<? extends long[]>": "",
    "char[]": "",
    "java.util.LinkedHashMap<String,Method>": "",
    "TypeToken<Map<String,Integer>>": "",
    "java.lang.Throwable": "",
    "AnnotationStringConverterFactory": "AnnotationStringConverterFactory",
    "ToStringConverter<T>": "",
    "java.lang.Class<? extends Double[]>": "",
    "StringConverter<DistanceNoAnnotationsCharSequence>": "",
    "java.lang.IllegalArgumentException": "",
    "GenericArrayTypeImpl": "GenericArrayTypeImpl",
    "TypedStringConverter<Short[]>": "",
    "java.text.ParseException": "",
    "void": "",
    "TestNumericArrayStringConverterFactory": "TestNumericArrayStringConverterFactory",
    "java.lang.ClassCastException": "",
    "java.util.List<>": "",
    "TypeCapture<int[]>": "",
    "java.util.concurrent.ConcurrentHashMap<Class<?>,TypedStringConverter<?>>": "",
    "HasCodeInterface<String>": "",
    "java.lang.Object": "",
    "java.lang.Enum<>": "",
    "TypedStringConverter<SubMethodMethod>": "",
    "java.util.HashSet<Class<?>>": "",
    "java.lang.Byte[]": "",
    "java.net.InetAddress": "",
    "java.lang.Class<T>": "",
    "DoubleArrayStringConverter": "DoubleArrayStringConverter",
    "TypedStringConverter<?>": "",
    "java.lang.IndexOutOfBoundsException": "",
    "java.math.BigInteger": "",
    "TypedAdapter": "TypedAdapter",
    "java.lang.Class<? extends Object>": "",
    "TypeTokenStringConverter": "TypeTokenStringConverter",
    "IntArrayStringConverter": "IntArrayStringConverter",
    "ParameterizedTypeImpl": "ParameterizedTypeImpl",
    "DistanceWithFactoryFactory": "DistanceWithFactoryFactory",
    "DistanceToStringInvalidParameters": "DistanceToStringInvalidParameters",
    "java.lang.Short[]": "",
    "java.lang.reflect.AnnotatedElement": "",
    "java.util.List<Type>": "",
    "TypedStringConverter<Character[]>": "",
    "TypedStringConverter<DistanceMethodMethod>": "",
    "TypedStringConverter<Test3Class>": "",
    "MockDistanceStringConverter": "MockDistanceStringConverter",
    "java.lang.Number": "",
    "java.io.PrintStream": "",
    "java.lang.Class<? extends Validity>": "",
    "TypedAdapter<>": "",
    "Test3SuperClass": "Test3SuperClass",
    "DistanceFromStringException": "DistanceFromStringException",
    "java.lang.Class<? extends int[]>": "",
    "TestGuavaTypeTokenStringConverter": "TestGuavaTypeTokenStringConverter",
    "ClassOwnership": "ClassOwnership",
    "java.lang.reflect.Type": "",
    "java.lang.System": "",
    "java.util.concurrent.ConcurrentHashMap<String,Enum<?>>": "",
    "DistanceTwoFromStringMethodAnnotations": "DistanceTwoFromStringMethodAnnotations",
    "Test2Factory": "Test2Factory",
    "ValidityCheck": "ValidityCheck",
    "java.lang.UnsupportedOperationException": "",
    "StringConverter<?>": "",
    "FloatArrayStringConverter": "FloatArrayStringConverter",
    "TypedStringConverter<R>": "",
    "java.lang.Class<? extends double[]>": "",
    "EnumStringConverter": "EnumStringConverter",
    "java.lang.Class<? extends short[]>": "",
    "java.lang.Enum<?>": "",
    "OptionalLongStringConverter": "OptionalLongStringConverter",
    "TestNumericObjectArrayStringConverterFactory": "TestNumericObjectArrayStringConverterFactory",
    "java.util.Arrays": "",
    "java.util.Map<? super String,? super Integer>": "",
    "TypedStringConverter<Type>": "",
    "java.io.File": "",
    "java.util.List<String>": "",
    "java.util.Map<String,? extends List<? extends Integer>>": "",
    "java.lang.NullPointerException": "",
    "HasCodeInterface": "HasCodeInterface",
    "TypedStringConverter<RoundingMode>": "",
    "NativeTypeVariableEquals": "NativeTypeVariableEquals",
    "Test3Factory": "Test3Factory",
    "TypedStringConverter<long[]>": "",
    "ConstructorFromStringConverter<T>": "",
    "TestStringConvert": "TestStringConvert",
    "java.lang.Class<? extends Integer[]>": "",
    "java.util.Calendar": "",
    "SuperFactorySub": "SuperFactorySub",
    "java.lang.Boolean[]": "",
    "TypedFromStringConverter<T>": "",
    "java.util.Currency": "",
    "FromStringConverter": "FromStringConverter",
    "TypedStringConverter<HasCodeImpl>": "",
    "DistanceToStringNoFromString": "DistanceToStringNoFromString",
    "TypedStringConverter<Double[]>": "",
    "java.util.Map<Integer,Double>": "",
    "NumericObjectArrayStringConverterFactory": "NumericObjectArrayStringConverterFactory",
    "java.util.Map<? super Integer,? extends List<? extends Number>>": "",
    "DistanceFromStringInvalidParameterCount": "DistanceFromStringInvalidParameterCount",
    "java.lang.reflect.Method": "",
    "java.lang.SecurityException": "",
    "TypeToken<Map<String,Map<? super Integer,? extends List<? extends Number>>>>": "",
    "java.lang.Long[]": "",
    "java.lang.annotation.RetentionPolicy": "",
    "Test3Interface": "Test3Interface",
    "TypedStringConverter<SuperFactorySub>": "",
    "java.util.concurrent.ConcurrentHashMap<String,Class<?>>": "",
    "DistanceToStringInvalidReturnType": "DistanceToStringInvalidReturnType",
    "java.lang.Exception": "",
    "java.lang.reflect.Modifier": "",
    "TypedStringConverter<Enum<?>>": "",
    "StringConverter<DistanceMethodMethod>": "",
    "SubMethodMethod": "SubMethodMethod",
    "java.lang.String": "",
    "BooleanArrayStringConverter": "BooleanArrayStringConverter",
    "TypeToken<Map<? super String,? super Integer>>": "",
    "java.lang.Package": "",
    "java.util.Enumeration<URL>": "",
    "java.lang.reflect.GenericArrayType": "",
    "java.util.Map<String,Map<? super Integer,? extends List<? extends Number>>>": "",
    "SubMethodConstructor": "SubMethodConstructor",
    "byte": "",
    "TypeVariableInvocationHandler": "TypeVariableInvocationHandler",
    "java.lang.reflect.ParameterizedType": "",
    "TypedStringConverter<Test2Class>": "",
    "Test4Factory": "Test4Factory",
    "ToStringConverter<DistanceNoAnnotations>": "",
    "TestJDKStringConverters": "TestJDKStringConverters",
    "java.util.Map<>": "",
    "java.lang.Class<? extends Character[]>": "",
    "java.lang.reflect.Constructor<T>": "",
    "java.lang.Boolean": "",
    "java.lang.Integer": "",
    "TestRenameHandlerBadInit": "TestRenameHandlerBadInit",
    "MethodFromStringConverter<>": "",
    "int[]": "",
    "DistanceFromStringInvalidReturnType": "DistanceFromStringInvalidReturnType",
    "ByteObjectArrayStringConverterFactory": "ByteObjectArrayStringConverterFactory",
    "StringConverter<R>": "",
    "java.util.concurrent.atomic.AtomicBoolean": "",
    "java.lang.Double": "",
    "java.util.List<? extends Integer>": "",
    "java.lang.Class<? extends T>": "",
    "java.net.UnknownHostException": "",
    "java.lang.IllegalAccessException": "",
    "java.math.RoundingMode": "",
    "Validity": "Validity",
    "java.lang.Class<? extends boolean[]>": "",
    "NumericArrayStringConverterFactory": "NumericArrayStringConverterFactory",
    "java.util.concurrent.ConcurrentHashMap<Class<?>,FromStringConverter<?>>": "",
    "java.lang.reflect.Proxy": "",
    "java.lang.Thread": "",
    "short": "",
    "TypeCapture": "TypeCapture",
    "TypeVariableImpl": "TypeVariableImpl",
    "TestJavaTime": "TestJavaTime",
    "ConstructorFromStringConverter": "ConstructorFromStringConverter",
    "SuperFactorySuper": "SuperFactorySuper",
    "java.util.Map<String,Class<?>>": "",
    "java.util.HashSet<Type>": "",
    "java.lang.annotation.ElementType": "",
    "long[]": "",
    "T": "",
    "java.util.Collections": "",
    "Test1Interface": "Test1Interface",
    "StringConverter<DistanceFromStringException>": "",
    "java.lang.Long": "",
    "TestBooleanObjectArrayStringConverterFactory": "TestBooleanObjectArrayStringConverterFactory",
    "Status": "Status",
    "ReflectionStringConverter<T>": "",
    "java.net.URI": "",
    "LocalClass<>": "",
    "StringConverter<Object>": "",
    "DistanceFromStringInvalidParameter": "DistanceFromStringInvalidParameter",
    "char": "",
    "TypedStringConverter<SuperFactorySuper>": "",
    "TypeToken<Map<String,Map<Integer,Double>>>": "",
    "java.text.SimpleDateFormat": "",
    "java.util.List<String[]>": "",
    "LongArrayStringConverter": "LongArrayStringConverter",
    "TypedStringConverter<T>": "",
    "java.lang.Class<? extends DistanceNoAnnotations>": "",
    "java.lang.reflect.TypeVariable<?>": "",
    "StringConverter<DistanceNoAnnotations>": "",
    "TestByteObjectArrayStringConverterFactory": "TestByteObjectArrayStringConverterFactory",
    "EnumStringConverterFactory": "EnumStringConverterFactory",
    "DistanceNoAnnotationsCharSequence": "DistanceNoAnnotationsCharSequence",
    "java.lang.Class<? extends float[]>": "",
    "MockIntegerStringConverter": "MockIntegerStringConverter",
    "java.util.Map<>.Entry<String,int[][]>": "",
    "StringConverter<Validity>": "",
    "java.util.Map<String,Method>": "",
    "java.util.HashMap<String,Enum<?>>": "",
    "TypedStringConverter<Test1Class>": "",
    "TypedStringConverter<Float[]>": "",
    "LocalClass": "LocalClass",
    "java.lang.Character[]": "",
    "DistanceMethodConstructorCharSequence": "DistanceMethodConstructorCharSequence",
    "LocalClass<String>": "",
    "DistanceMethodConstructor": "DistanceMethodConstructor",
    "TestStringConverterFactory": "TestStringConverterFactory",
    "TypedStringConverter<DistanceWithFactory>": "",
    "DistanceFromStringNoToString": "DistanceFromStringNoToString",
    "ReflectionStringConverter<?>": "",
    "FromStringConverter<?>": "",
    "TestRenameHandler": "TestRenameHandler",
    "DistanceWithFactory": "DistanceWithFactory",
    "java.lang.Class<? extends DistanceMethodMethod>": "",
    "C": "",
    "java.lang.reflect.Array": "",
    "java.util.Map<String,List<Integer>>": "",
    "TypedStringConverter<Test2Interface>": "",
    "java.util.HashMap<String,Class<?>>": "",
    "java.util.UUID": "",
    "java.util.concurrent.atomic.AtomicInteger": "",
    "java.nio.charset.Charset": "",
    "java.util.List<? super Integer>": "",
    "java.util.GregorianCalendar": "",
    "ToStringConverter": "ToStringConverter",
    "FromStringConverter<DistanceNoAnnotations>": "",
    "TypedStringConverter": "TypedStringConverter",
    "StringConverter<Integer>": ""
}