{
    "DefaultPooledObject<Object>": "",
    "EvictionConfig": "EvictionConfig",
    "BaseObjectPool": "BaseObjectPool",
    "TestKeyedObjectPool": "TestKeyedObjectPool",
    "java.util.HashMap<K,TimerTask>": "",
    "java.util.Collection<>": "List",
    "SynchronizedKeyedObjectPool": "SynchronizedKeyedObjectPool",
    "BaseObjectPoolConfig": "BaseObjectPoolConfig",
    "FailingKeyedPooledObjectFactory": "FailingKeyedPooledObjectFactory",
    "ErodingFactor": "ErodingFactor",
    "ObjectPool<>": "List[object]",
    "java.util.TimerTask": "",
    "java.lang.ref.WeakReference<>": "",
    "CallStack": "CallStack",
    "Waiter": "Waiter",
    "EvictionIterator": "EvictionIterator",
    "java.util.concurrent.atomic.AtomicInteger": "int",
    "PooledObject<V>": "PooledObject",
    "MethodCall": "MethodCall",
    "java.util.concurrent.locks.ReentrantReadWriteLock": "",
    "PooledObjectFactory<T>": "PooledObjectFactory",
    "UsageTracking<T>": "",
    "FactoryDE": "FactoryDE",
    "BasePooledObjectFactory<B>": "",
    "java.lang.ThreadDeath": "",
    "java.lang.reflect.InvocationTargetException": "Exception",
    "KeyedObjectPool<>": "collections.OrderedDict",
    "BasePooledObjectFactory<String>": "",
    "TestObjectPool": "TestObjectPool",
    "java.net.URL": "",
    "TestBaseKeyedPoolableObjectFactory": "TestBaseKeyedPoolableObjectFactory",
    "java.lang.Exception": "Exception",
    "E": "Any",
    "java.util.HashMap<WeakReference<Runnable>,WeakRunner>": "",
    "VisitTracker<K>": "",
    "KeyedObjectPool": "KeyedObjectPool",
    "PooledObject<Foo>": "",
    "java.lang.reflect.ParameterizedType": "",
    "SleepingObjectFactory": "SleepingObjectFactory",
    "ProxySource<T>": "ProxySource",
    "LinkedBlockingDeque": "LinkedBlockingDeque",
    "KeyedObjectPoolMinIdleTimerTask<K,V>": "",
    "SynchronizedKeyedPooledObjectFactory<K,V>": "",
    "java.util.HashMap<K,Integer>": "",
    "PooledSoftReference<String>": "",
    "D": "",
    "java.util.Collection<Integer>": "List[int]",
    "GenericKeyedObjectPoolMXBean": "GenericKeyedObjectPoolMXBean",
    "TestConstants": "TestConstants",
    "java.lang.StringBuilder": "str",
    "java.lang.NullPointerException": "None",
    "TestPoolImplUtils": "TestPoolImplUtils",
    "java.lang.Class<T>": "Type",
    "AbandonedConfig": "AbandonedConfig",
    "java.util.Map<String,Integer>": "Dict[str, int]",
    "NotSimpleFactory": "NotSimpleFactory",
    "GenericObjectPoolConfig": "GenericObjectPoolConfig",
    "java.io.PrintWriter": "io.TextIOWrapper",
    "ErodingPerKeyKeyedObjectPool<K,V>": "",
    "BaseGenericObjectPool<?>": "",
    "EvictionTimer": "EvictionTimer",
    "PooledObjectFactory": "PooledObjectFactory",
    "java.lang.UnsupportedOperationException": "RuntimeError",
    "java.text.DateFormat": "datetime.datetime",
    "SynchronizedKeyedObjectPool<K,V>": "",
    "java.lang.Runtime": "",
    "StatsStore": "StatsStore",
    "PooledObjectFactory<Object>": "",
    "java.lang.Comparable<PooledObject>": "",
    "float": "float",
    "JdkProxyHandler<T>": "",
    "java.lang.Object": "object",
    "java.util.Collection<String>": "List[str]",
    "java.util.HashMap<K,V>": "Dict",
    "UsageTracking<>": "UsageTracking",
    "DefaultPooledObject": "DefaultPooledObject",
    "java.lang.ref.SoftReference<T>": "",
    "V": "Any",
    "AssertionFailedError": "AssertionError",
    "java.lang.Thread": "",
    "InterruptibleReentrantLock": "InterruptibleReentrantLock",
    "java.util.Set<String>": "Set[str]",
    "java.util.List<String>": "List[str]",
    "java.util.Set<DefaultPooledObjectInfo>": "Set[DefaultPooledObjectInfo]",
    "ProxiedKeyedObjectPool": "ProxiedKeyedObjectPool",
    "DefaultPooledObjectInfoMBean": "DefaultPooledObjectInfoMBean",
    "java.util.function.Predicate<MethodCall>": "typing.Callable[[MethodCall], bool]",
    "GenericKeyedObjectPoolConfig<>": "GenericKeyedObjectPoolConfig",
    "K": "",
    "IdentityWrapper<>": "IdentityWrapper",
    "Foo": "Foo",
    "ObjectPool<String>": "List[str]",
    "double": "float",
    "PooledObjectFactory<>": "PooledObjectFactory",
    "VisitTracker": "VisitTracker",
    "SynchronizedPooledObjectFactory": "SynchronizedPooledObjectFactory",
    "GenericObjectPoolMXBean": "GenericObjectPoolMXBean",
    "PooledObject<Long>": "",
    "java.lang.SecurityManager": "",
    "KeyedObjectPool<K,V>": "Dict",
    "java.lang.reflect.Type": "Type",
    "PrivateException": "PrivateException",
    "java.util.concurrent.atomic.AtomicLong[]": "List[int]",
    "DefaultPooledObjectInfo": "DefaultPooledObjectInfo",
    "java.util.stream.Collectors": "itertools.groupby",
    "java.lang.InternalError": "",
    "BaseObjectPoolConfig<T>": "",
    "java.io.ObjectInputStream": "builtins.object",
    "java.util.List<Object>": "List[object]",
    "KeyedObjectPool<String,TestObject>": "Dict[str, TestObject]",
    "ObjectPool": "ObjectPool",
    "FactoryF<Integer>": "typing.TypeVar('FactoryF', bound=int)",
    "DefaultTrackedUse": "DefaultTrackedUse",
    "FactoryAB": "FactoryAB",
    "DestroyMode": "DestroyMode",
    "MethodCallPoolableObjectFactory": "MethodCallPoolableObjectFactory",
    "PooledObject<?>": "typing.Any",
    "ErodingObjectPool": "ErodingObjectPool",
    "AbstractItr": "AbstractItr",
    "GenericKeyedObjectPoolConfig": "GenericKeyedObjectPoolConfig",
    "A": "object",
    "BaseProxyHandler": "BaseProxyHandler",
    "java.util.Timer": "",
    "ErodingKeyedObjectPool<>": "ErodingKeyedObjectPool",
    "SynchronizedPooledObjectFactory<T>": "SynchronizedPooledObjectFactory",
    "java.util.List<MethodCall>": "List[MethodCall]",
    "PoolUtils": "PoolUtils",
    "BaseGenericObjectPool": "BaseGenericObjectPool",
    "TestObject": "TestObject",
    "FactoryAB<B,A>": "",
    "Node": "Node",
    "java.lang.reflect.Proxy": "",
    "EvictionPolicy": "EvictionPolicy",
    "PooledSoftReference": "PooledSoftReference",
    "java.util.concurrent.atomic.AtomicBoolean": "bool",
    "java.io.Closeable": "io.IOBase",
    "java.util.Deque<PooledObject>": "collections.deque",
    "java.time.Instant": "datetime.datetime",
    "WeakRunner": "WeakRunner",
    "NoOpCallStack": "NoOpCallStack",
    "BaseObject": "BaseObject",
    "ObjectPoolMinIdleTimerTask": "ObjectPoolMinIdleTimerTask",
    "boolean": "bool",
    "java.lang.ClassNotFoundException": "ModuleNotFoundError",
    "ProxySource<V>": "ProxySource",
    "CglibProxySource": "CglibProxySource",
    "java.lang.Class<?>[]": "List[Type]",
    "NoOpCallStackTest": "NoOpCallStackTest",
    "EvictionPolicy<T>": "EvictionPolicy",
    "java.lang.reflect.TypeVariable<>": "typing.TypeVar",
    "java.util.concurrent.ExecutorService": "",
    "java.lang.reflect.InvocationHandler": "object",
    "CallStackTest": "CallStackTest",
    "TestGenericObjectPoolClassLoaders": "TestGenericObjectPoolClassLoaders",
    "DefaultPooledObject<T>": "DefaultPooledObject",
    "IdentityWrapper<T>": "",
    "java.util.stream.Stream<WeakReference<Class<?>>>": "",
    "java.util.Map<String,List<DefaultPooledObjectInfo>>": "Dict[str, List[DefaultPooledObjectInfo]]",
    "KeyedPooledObjectFactory<K,V>": "",
    "EvictionPolicy<>": "EvictionPolicy",
    "PooledObject<Object>": "",
    "long": "int",
    "PooledObject<Integer>": "",
    "java.util.Deque<E>": "collections.deque",
    "ObjectPool<Object>": "List[object]",
    "FactoryC": "FactoryC",
    "LinkedBlockingDeque<Object>": "collections.deque",
    "java.lang.Runnable": "",
    "java.util.concurrent.Executors": "",
    "java.util.ArrayList<Integer>": "List[int]",
    "KeyedPooledObjectFactory<Object,Object>": "",
    "SynchronizedKeyedPooledObjectFactory": "SynchronizedKeyedPooledObjectFactory",
    "TimerHolder": "TimerHolder",
    "java.lang.CloneNotSupportedException": "Exception",
    "Snapshot": "Snapshot",
    "java.util.concurrent.locks.ReadLock": "",
    "ProxiedObjectPool": "ProxiedObjectPool",
    "java.util.Collection<K>": "",
    "PoolImplUtils": "PoolImplUtils",
    "java.lang.ClassLoader": "",
    "java.util.Map<K,TimerTask>": "",
    "ThrowableCallStack": "ThrowableCallStack",
    "java.lang.Long": "int",
    "java.io.Serializable": "object",
    "java.lang.ref.WeakReference<Class<?>>": "",
    "java.time.Duration": "datetime.timedelta",
    "UsageTracking<V>": "",
    "TestSynchronizedPooledObjectFactory": "TestSynchronizedPooledObjectFactory",
    "java.util.concurrent.locks.Condition": "",
    "ProxySource": "ProxySource",
    "java.util.function.Consumer<PooledObject<T>>": "",
    "PooledObject<String>": "",
    "java.util.List<DefaultPooledObjectInfo>": "List[DefaultPooledObjectInfo]",
    "TestBaseObjectPool": "TestBaseObjectPool",
    "DefaultEvictionPolicy": "DefaultEvictionPolicy",
    "java.lang.AssertionError": "AssertionError",
    "PoolTest": "PoolTest",
    "ObjectPool<TestObject>": "List[TestObject]",
    "java.util.concurrent.atomic.AtomicReference<Duration>": "",
    "java.util.E": "",
    "TestDefaultPooledObject": "TestDefaultPooledObject",
    "CallStackUtils": "CallStackUtils",
    "PooledObject<T>": "",
    "java.util.HashSet<String>": "Set[str]",
    "java.io.ObjectOutputStream": "pickle",
    "java.lang.ref.SoftReference<String>": "",
    "F": "",
    "java.util.concurrent.Future<?>": "",
    "PrivateSecurityManager": "PrivateSecurityManager",
    "DescendingItr": "DescendingItr",
    "BaseKeyedPooledObjectFactory": "BaseKeyedPooledObjectFactory",
    "java.util.Iterator<K>": "",
    "KeyedObjectPool<String,Object>": "Dict[str, object]",
    "java.util.List<WeakReference<Class<?>>>": "",
    "LinkedBlockingDeque<Integer>": "collections.deque",
    "java.lang.InstantiationException": "",
    "java.util.Map<IdentityWrapper<T>,PooledObject<T>>": "",
    "Itr": "Itr",
    "java.net.URLClassLoader": "",
    "java.text.SimpleDateFormat": "datetime.datetime",
    "ErodingObjectPool<T>": "",
    "int": "int",
    "java.io.Writer": "io.TextIOWrapper",
    "java.util.Iterator<PooledObject<T>>": "",
    "BaseObjectPoolConfig<>": "BaseObjectPoolConfig",
    "java.util.Iterator<Integer>": "Iterator[int]",
    "FactoryF": "FactoryF",
    "SwallowedExceptionListener": "SwallowedExceptionListener",
    "java.util.concurrent.ScheduledFuture<?>": "",
    "void": "None",
    "CustomClassLoader": "CustomClassLoader",
    "ProxySource<TestObject>": "List[TestObject]",
    "java.io.OutputStreamWriter": "io.TextIOWrapper",
    "BaseTestProxiedObjectPool": "BaseTestProxiedObjectPool",
    "DefaultEvictionPolicy<>": "DefaultEvictionPolicy",
    "ErodingKeyedObjectPool<K,V>": "",
    "Evictor": "Evictor",
    "java.util.NoSuchElementException": "",
    "C": "Any",
    "TestLinkedBlockingDeque": "TestLinkedBlockingDeque",
    "java.lang.reflect.Method": "",
    "java.util.Entry<WeakReference<Runnable>,WeakRunner>": "",
    "ErodingPerKeyKeyedObjectPool": "ErodingPerKeyKeyedObjectPool",
    "java.lang.ref.WeakReference<Runnable>": "",
    "FactoryDE<Long,F>": "",
    "java.lang.Class<?>": "Type",
    "PooledObject<VisitTracker<K>>": "",
    "PooledObject": "PooledObject",
    "java.nio.charset.Charset": "str",
    "java.util.Collections": "collections",
    "KeyedObjectPool<Object,Object>": "Dict",
    "java.util.List<AtomicLong>": "List[int]",
    "java.io.StringWriter": "io.StringIO",
    "java.util.Objects": "builtins.object",
    "PoolUtils.TimerHolder": "",
    "java.lang.reflect.Array": "List",
    "java.util.ArrayList<MethodCall>": "List[MethodCall]",
    "java.lang.Class<>": "typing.Type",
    "java.lang.Integer": "int",
    "java.util.AbstractQueue<E>": "collections.abc.Collection",
    "TestPoolUtils": "TestPoolUtils",
    "java.util.ArrayList<String>": "List[str]",
    "java.util.Map<K,Integer>": "",
    "java.lang.Throwable": "Exception",
    "PooledObject<Waiter>": "",
    "FactoryC<D>": "",
    "FactoryBA<C,String>": "",
    "java.lang.ClassCastException": "TypeError",
    "Reaper": "Reaper",
    "PooledFooFactory": "PooledFooFactory",
    "TestObjectImpl": "TestObjectImpl",
    "java.util.Iterator<E>": "Iterator[Any]",
    "java.lang.Class<? extends PooledObjectFactory<>>": "typing.Type[PooledObjectFactory]",
    "java.lang.CharSequence": "str",
    "java.util.Collection<? super E>": "collections.abc.Collection",
    "java.util.concurrent.atomic.AtomicLong": "int",
    "VisitTrackerFactory": "VisitTrackerFactory",
    "TestEvictionConfig": "TestEvictionConfig",
    "java.lang.Class<? extends T>": "",
    "java.lang.Object[]": "List",
    "java.lang.Cloneable": "object",
    "WaiterFactory<>": "WaiterFactory",
    "PooledObjectState": "PooledObjectState",
    "java.util.function.Function<Class<?>,WeakReference<Class<?>>>": "",
    "java.util.Deque<PooledObject<T>>": "",
    "T[]": "List",
    "java.lang.InterruptedException": "builtins.InterruptedError",
    "SimpleFactory": "SimpleFactory",
    "TestPooledSoftReference": "TestPooledSoftReference",
    "SynchronizedObjectPool": "SynchronizedObjectPool",
    "java.util.concurrent.ScheduledThreadPoolExecutor": "",
    "java.time.Clock": "datetime.datetime",
    "java.lang.String": "str",
    "java.util.Map<K,ErodingFactor>": "",
    "BaseGenericObjectPool<?>.Evictor<>": "",
    "java.util.Collection<? extends E>": "List[Any]",
    "B": "",
    "java.util.concurrent.TimeUnit": "",
    "JdkProxyHandler": "JdkProxyHandler",
    "ObjectPool<T>": "List",
    "java.util.ArrayList<PooledObject<T>>": "",
    "java.lang.VirtualMachineError": "",
    "java.lang.IllegalAccessException": "Exception",
    "java.util.Collection<?>": "List[object]",
    "IdentityWrapper": "IdentityWrapper",
    "java.lang.RuntimeException": "RuntimeError",
    "WaiterFactory": "WaiterFactory",
    "SynchronizedObjectPool<T>": "",
    "TestTrackedUse": "TestTrackedUse",
    "java.util.function.Consumer<Thread>": "",
    "LinkedBlockingDeque<>": "collections.deque",
    "TrackedUse": "TrackedUse",
    "ErodingKeyedObjectPool": "ErodingKeyedObjectPool",
    "T": "Any",
    "java.lang.IllegalArgumentException": "ValueError",
    "java.util.stream.Stream<>": "List",
    "Executable": "Callable",
    "java.util.List<Future<?>>": "",
    "BaseProxyHandler<T>": "",
    "BaseObjectPool<Object>": "",
    "java.lang.Class<PooledObjectFactory<>>": "typing.Type[PooledObjectFactory]",
    "java.lang.Boolean": "bool",
    "java.time.temporal.ChronoUnit": "datetime.timedelta",
    "java.lang.NoSuchMethodException": "",
    "ObjectPoolMinIdleTimerTask<T>": "ObjectPoolMinIdleTimerTask",
    "Node<E>": "List",
    "java.util.ArrayList<Future<?>>": "",
    "java.lang.IllegalStateException": "RuntimeError",
    "FactoryBA": "FactoryBA",
    "UsageTracking": "UsageTracking",
    "java.lang.System": "sys",
    "java.util.concurrent.locks.ReentrantLock": "",
    "KeyedPooledObjectFactory": "KeyedPooledObjectFactory",
    "BaseTestProxiedKeyedObjectPool": "BaseTestProxiedKeyedObjectPool",
    "java.util.concurrent.locks.WriteLock": "",
    "MethodCallLogger": "MethodCallLogger",
    "PooledObject<>": "PooledObject",
    "java.util.Map<String,TimerTask>": "",
    "KeyedObjectPool<String,String>": "Dict[str, str]",
    "JdkProxySource": "JdkProxySource",
    "java.lang.reflect.TypeVariable<?>": "TypeVar",
    "BasePooledObjectFactory": "BasePooledObjectFactory",
    "SecurityManagerCallStack": "SecurityManagerCallStack",
    "java.util.Arrays": "List",
    "KeyedObjectPoolMinIdleTimerTask": "KeyedObjectPoolMinIdleTimerTask",
    "java.lang.Math": ""
}