{
    "StringDecoder": [
        [
            "Decoder",
            "org.apache.commons.codec.Decoder"
        ],
        [
            "DecoderException",
            "org.apache.commons.codec.DecoderException"
        ]
    ],
    "StringEncoder": [
        [
            "Encoder",
            "org.apache.commons.codec.Encoder"
        ],
        [
            "EncoderException",
            "org.apache.commons.codec.EncoderException"
        ]
    ],
    "Resources": [],
    "CodecPolicy": [],
    "Charsets": [],
    "DecoderException": [],
    "EncoderException": [],
    "Encoder": [
        [
            "EncoderException",
            "org.apache.commons.codec.EncoderException"
        ]
    ],
    "StringEncoderComparator": [
        [
            "EncoderException",
            "org.apache.commons.codec.EncoderException"
        ],
        [
            "StringEncoder",
            "org.apache.commons.codec.StringEncoder"
        ]
    ],
    "BinaryEncoder": [
        [
            "Encoder",
            "org.apache.commons.codec.Encoder"
        ],
        [
            "EncoderException",
            "org.apache.commons.codec.EncoderException"
        ]
    ],
    "BinaryDecoder": [
        [
            "Decoder",
            "org.apache.commons.codec.Decoder"
        ],
        [
            "DecoderException",
            "org.apache.commons.codec.DecoderException"
        ]
    ],
    "CharEncoding": [],
    "Decoder": [
        [
            "DecoderException",
            "org.apache.commons.codec.DecoderException"
        ]
    ],
    "QCodec": [
        [
            "DecoderException",
            "org.apache.commons.codec.DecoderException"
        ],
        [
            "EncoderException",
            "org.apache.commons.codec.EncoderException"
        ],
        [
            "StringDecoder",
            "org.apache.commons.codec.StringDecoder"
        ],
        [
            "StringEncoder",
            "org.apache.commons.codec.StringEncoder"
        ],
        [
            "QuotedPrintableCodec",
            "org.apache.commons.codec.net.QuotedPrintableCodec"
        ],
        [
            "RFC1522Codec",
            "org.apache.commons.codec.net.RFC1522Codec"
        ]
    ],
    "PercentCodec": [
        [
            "BinaryDecoder",
            "org.apache.commons.codec.BinaryDecoder"
        ],
        [
            "BinaryEncoder",
            "org.apache.commons.codec.BinaryEncoder"
        ],
        [
            "DecoderException",
            "org.apache.commons.codec.DecoderException"
        ],
        [
            "EncoderException",
            "org.apache.commons.codec.EncoderException"
        ],
        [
            "Utils",
            "org.apache.commons.codec.net.Utils"
        ]
    ],
    "QuotedPrintableCodec": [
        [
            "BinaryDecoder",
            "org.apache.commons.codec.BinaryDecoder"
        ],
        [
            "BinaryEncoder",
            "org.apache.commons.codec.BinaryEncoder"
        ],
        [
            "DecoderException",
            "org.apache.commons.codec.DecoderException"
        ],
        [
            "EncoderException",
            "org.apache.commons.codec.EncoderException"
        ],
        [
            "StringDecoder",
            "org.apache.commons.codec.StringDecoder"
        ],
        [
            "StringEncoder",
            "org.apache.commons.codec.StringEncoder"
        ],
        [
            "StringUtils",
            "org.apache.commons.codec.binary.StringUtils"
        ],
        [
            "Utils",
            "org.apache.commons.codec.net.Utils"
        ]
    ],
    "RFC1522Codec": [
        [
            "DecoderException",
            "org.apache.commons.codec.DecoderException"
        ],
        [
            "EncoderException",
            "org.apache.commons.codec.EncoderException"
        ],
        [
            "StringUtils",
            "org.apache.commons.codec.binary.StringUtils"
        ]
    ],
    "URLCodec": [
        [
            "BinaryDecoder",
            "org.apache.commons.codec.BinaryDecoder"
        ],
        [
            "BinaryEncoder",
            "org.apache.commons.codec.BinaryEncoder"
        ],
        [
            "CharEncoding",
            "org.apache.commons.codec.CharEncoding"
        ],
        [
            "DecoderException",
            "org.apache.commons.codec.DecoderException"
        ],
        [
            "EncoderException",
            "org.apache.commons.codec.EncoderException"
        ],
        [
            "StringDecoder",
            "org.apache.commons.codec.StringDecoder"
        ],
        [
            "StringEncoder",
            "org.apache.commons.codec.StringEncoder"
        ],
        [
            "StringUtils",
            "org.apache.commons.codec.binary.StringUtils"
        ],
        [
            "Utils",
            "org.apache.commons.codec.net.Utils"
        ]
    ],
    "BCodec": [
        [
            "CodecPolicy",
            "org.apache.commons.codec.CodecPolicy"
        ],
        [
            "DecoderException",
            "org.apache.commons.codec.DecoderException"
        ],
        [
            "EncoderException",
            "org.apache.commons.codec.EncoderException"
        ],
        [
            "StringDecoder",
            "org.apache.commons.codec.StringDecoder"
        ],
        [
            "StringEncoder",
            "org.apache.commons.codec.StringEncoder"
        ],
        [
            "Base64",
            "org.apache.commons.codec.binary.Base64"
        ],
        [
            "BaseNCodec",
            "org.apache.commons.codec.binary.BaseNCodec"
        ],
        [
            "RFC1522Codec",
            "org.apache.commons.codec.net.RFC1522Codec"
        ]
    ],
    "Utils": [
        [
            "DecoderException",
            "org.apache.commons.codec.DecoderException"
        ]
    ],
    "Digest": [
        [
            "Hex",
            "org.apache.commons.codec.binary.Hex"
        ]
    ],
    "Base16OutputStream": [
        [
            "CodecPolicy",
            "org.apache.commons.codec.CodecPolicy"
        ],
        [
            "Base16",
            "org.apache.commons.codec.binary.Base16"
        ],
        [
            "BaseNCodec",
            "org.apache.commons.codec.binary.BaseNCodec"
        ],
        [
            "BaseNCodecOutputStream",
            "org.apache.commons.codec.binary.BaseNCodecOutputStream"
        ]
    ],
    "Base32OutputStream": [
        [
            "CodecPolicy",
            "org.apache.commons.codec.CodecPolicy"
        ],
        [
            "Base32",
            "org.apache.commons.codec.binary.Base32"
        ],
        [
            "BaseNCodec",
            "org.apache.commons.codec.binary.BaseNCodec"
        ],
        [
            "BaseNCodecOutputStream",
            "org.apache.commons.codec.binary.BaseNCodecOutputStream"
        ]
    ],
    "StringUtils": [
        [
            "CharSequenceUtils",
            "org.apache.commons.codec.binary.CharSequenceUtils"
        ]
    ],
    "BaseNCodec": [
        [
            "BinaryDecoder",
            "org.apache.commons.codec.BinaryDecoder"
        ],
        [
            "BinaryEncoder",
            "org.apache.commons.codec.BinaryEncoder"
        ],
        [
            "CodecPolicy",
            "org.apache.commons.codec.CodecPolicy"
        ],
        [
            "DecoderException",
            "org.apache.commons.codec.DecoderException"
        ],
        [
            "EncoderException",
            "org.apache.commons.codec.EncoderException"
        ],
        [
            "StringUtils",
            "org.apache.commons.codec.binary.StringUtils"
        ]
    ],
    "Base32InputStream": [
        [
            "CodecPolicy",
            "org.apache.commons.codec.CodecPolicy"
        ],
        [
            "Base32",
            "org.apache.commons.codec.binary.Base32"
        ],
        [
            "BaseNCodec",
            "org.apache.commons.codec.binary.BaseNCodec"
        ],
        [
            "BaseNCodecInputStream",
            "org.apache.commons.codec.binary.BaseNCodecInputStream"
        ]
    ],
    "Base16": [
        [
            "CodecPolicy",
            "org.apache.commons.codec.CodecPolicy"
        ],
        [
            "BaseNCodec",
            "org.apache.commons.codec.binary.BaseNCodec"
        ]
    ],
    "Base64": [
        [
            "CodecPolicy",
            "org.apache.commons.codec.CodecPolicy"
        ],
        [
            "BaseNCodec",
            "org.apache.commons.codec.binary.BaseNCodec"
        ],
        [
            "StringUtils",
            "org.apache.commons.codec.binary.StringUtils"
        ]
    ],
    "BaseNCodecInputStream": [
        [
            "BaseNCodec",
            "org.apache.commons.codec.binary.BaseNCodec"
        ]
    ],
    "CharSequenceUtils": [],
    "Hex": [
        [
            "BinaryDecoder",
            "org.apache.commons.codec.BinaryDecoder"
        ],
        [
            "BinaryEncoder",
            "org.apache.commons.codec.BinaryEncoder"
        ],
        [
            "CharEncoding",
            "org.apache.commons.codec.CharEncoding"
        ],
        [
            "DecoderException",
            "org.apache.commons.codec.DecoderException"
        ],
        [
            "EncoderException",
            "org.apache.commons.codec.EncoderException"
        ]
    ],
    "BaseNCodecOutputStream": [
        [
            "BaseNCodec",
            "org.apache.commons.codec.binary.BaseNCodec"
        ]
    ],
    "Base64InputStream": [
        [
            "CodecPolicy",
            "org.apache.commons.codec.CodecPolicy"
        ],
        [
            "Base64",
            "org.apache.commons.codec.binary.Base64"
        ],
        [
            "BaseNCodec",
            "org.apache.commons.codec.binary.BaseNCodec"
        ],
        [
            "BaseNCodecInputStream",
            "org.apache.commons.codec.binary.BaseNCodecInputStream"
        ]
    ],
    "Base64OutputStream": [
        [
            "CodecPolicy",
            "org.apache.commons.codec.CodecPolicy"
        ],
        [
            "Base64",
            "org.apache.commons.codec.binary.Base64"
        ],
        [
            "BaseNCodec",
            "org.apache.commons.codec.binary.BaseNCodec"
        ],
        [
            "BaseNCodecOutputStream",
            "org.apache.commons.codec.binary.BaseNCodecOutputStream"
        ]
    ],
    "Base16InputStream": [
        [
            "CodecPolicy",
            "org.apache.commons.codec.CodecPolicy"
        ],
        [
            "Base16",
            "org.apache.commons.codec.binary.Base16"
        ],
        [
            "BaseNCodec",
            "org.apache.commons.codec.binary.BaseNCodec"
        ],
        [
            "BaseNCodecInputStream",
            "org.apache.commons.codec.binary.BaseNCodecInputStream"
        ]
    ],
    "BinaryCodec": [
        [
            "BinaryDecoder",
            "org.apache.commons.codec.BinaryDecoder"
        ],
        [
            "BinaryEncoder",
            "org.apache.commons.codec.BinaryEncoder"
        ],
        [
            "DecoderException",
            "org.apache.commons.codec.DecoderException"
        ],
        [
            "EncoderException",
            "org.apache.commons.codec.EncoderException"
        ]
    ],
    "Base32": [
        [
            "CodecPolicy",
            "org.apache.commons.codec.CodecPolicy"
        ],
        [
            "BaseNCodec",
            "org.apache.commons.codec.binary.BaseNCodec"
        ],
        [
            "StringUtils",
            "org.apache.commons.codec.binary.StringUtils"
        ]
    ],
    "Caverphone": [
        [
            "EncoderException",
            "org.apache.commons.codec.EncoderException"
        ],
        [
            "StringEncoder",
            "org.apache.commons.codec.StringEncoder"
        ],
        [
            "Caverphone2",
            "org.apache.commons.codec.language.Caverphone2"
        ]
    ],
    "RefinedSoundex": [
        [
            "EncoderException",
            "org.apache.commons.codec.EncoderException"
        ],
        [
            "StringEncoder",
            "org.apache.commons.codec.StringEncoder"
        ],
        [
            "SoundexUtils",
            "org.apache.commons.codec.language.SoundexUtils"
        ]
    ],
    "Metaphone": [
        [
            "EncoderException",
            "org.apache.commons.codec.EncoderException"
        ],
        [
            "StringEncoder",
            "org.apache.commons.codec.StringEncoder"
        ]
    ],
    "MatchRatingApproachEncoder": [
        [
            "EncoderException",
            "org.apache.commons.codec.EncoderException"
        ],
        [
            "StringEncoder",
            "org.apache.commons.codec.StringEncoder"
        ]
    ],
    "DoubleMetaphone": [
        [
            "EncoderException",
            "org.apache.commons.codec.EncoderException"
        ],
        [
            "StringEncoder",
            "org.apache.commons.codec.StringEncoder"
        ],
        [
            "StringUtils",
            "org.apache.commons.codec.binary.StringUtils"
        ]
    ],
    "Nysiis": [
        [
            "EncoderException",
            "org.apache.commons.codec.EncoderException"
        ],
        [
            "StringEncoder",
            "org.apache.commons.codec.StringEncoder"
        ],
        [
            "SoundexUtils",
            "org.apache.commons.codec.language.SoundexUtils"
        ]
    ],
    "Soundex": [
        [
            "EncoderException",
            "org.apache.commons.codec.EncoderException"
        ],
        [
            "StringEncoder",
            "org.apache.commons.codec.StringEncoder"
        ],
        [
            "SoundexUtils",
            "org.apache.commons.codec.language.SoundexUtils"
        ]
    ],
    "AbstractCaverphone": [
        [
            "EncoderException",
            "org.apache.commons.codec.EncoderException"
        ],
        [
            "StringEncoder",
            "org.apache.commons.codec.StringEncoder"
        ]
    ],
    "Caverphone2": [
        [
            "AbstractCaverphone",
            "org.apache.commons.codec.language.AbstractCaverphone"
        ]
    ],
    "Caverphone1": [
        [
            "AbstractCaverphone",
            "org.apache.commons.codec.language.AbstractCaverphone"
        ]
    ],
    "DaitchMokotoffSoundex": [
        [
            "CharEncoding",
            "org.apache.commons.codec.CharEncoding"
        ],
        [
            "EncoderException",
            "org.apache.commons.codec.EncoderException"
        ],
        [
            "Resources",
            "org.apache.commons.codec.Resources"
        ],
        [
            "StringEncoder",
            "org.apache.commons.codec.StringEncoder"
        ]
    ],
    "SoundexUtils": [
        [
            "EncoderException",
            "org.apache.commons.codec.EncoderException"
        ],
        [
            "StringEncoder",
            "org.apache.commons.codec.StringEncoder"
        ]
    ],
    "ColognePhonetic": [
        [
            "EncoderException",
            "org.apache.commons.codec.EncoderException"
        ],
        [
            "StringEncoder",
            "org.apache.commons.codec.StringEncoder"
        ]
    ],
    "ResourceConstants": [
        [
            "CharEncoding",
            "org.apache.commons.codec.CharEncoding"
        ]
    ],
    "NameType": [],
    "RuleType": [],
    "Languages": [
        [
            "Resources",
            "org.apache.commons.codec.Resources"
        ],
        [
            "NameType",
            "org.apache.commons.codec.language.bm.NameType"
        ],
        [
            "ResourceConstants",
            "org.apache.commons.codec.language.bm.ResourceConstants"
        ]
    ],
    "Rule": [
        [
            "Resources",
            "org.apache.commons.codec.Resources"
        ],
        [
            "Languages",
            "org.apache.commons.codec.language.bm.Languages"
        ],
        [
            "NameType",
            "org.apache.commons.codec.language.bm.NameType"
        ],
        [
            "ResourceConstants",
            "org.apache.commons.codec.language.bm.ResourceConstants"
        ],
        [
            "RuleType",
            "org.apache.commons.codec.language.bm.RuleType"
        ]
    ],
    "PhoneticEngine": [
        [
            "Lang",
            "org.apache.commons.codec.language.bm.Lang"
        ],
        [
            "Languages",
            "org.apache.commons.codec.language.bm.Languages"
        ],
        [
            "NameType",
            "org.apache.commons.codec.language.bm.NameType"
        ],
        [
            "Rule",
            "org.apache.commons.codec.language.bm.Rule"
        ],
        [
            "RuleType",
            "org.apache.commons.codec.language.bm.RuleType"
        ]
    ],
    "Lang": [
        [
            "Resources",
            "org.apache.commons.codec.Resources"
        ],
        [
            "Languages",
            "org.apache.commons.codec.language.bm.Languages"
        ],
        [
            "NameType",
            "org.apache.commons.codec.language.bm.NameType"
        ],
        [
            "ResourceConstants",
            "org.apache.commons.codec.language.bm.ResourceConstants"
        ]
    ],
    "BeiderMorseEncoder": [
        [
            "EncoderException",
            "org.apache.commons.codec.EncoderException"
        ],
        [
            "StringEncoder",
            "org.apache.commons.codec.StringEncoder"
        ],
        [
            "NameType",
            "org.apache.commons.codec.language.bm.NameType"
        ],
        [
            "PhoneticEngine",
            "org.apache.commons.codec.language.bm.PhoneticEngine"
        ],
        [
            "RuleType",
            "org.apache.commons.codec.language.bm.RuleType"
        ]
    ],
    "MurmurHash2": [
        [
            "StringUtils",
            "org.apache.commons.codec.binary.StringUtils"
        ]
    ],
    "Md5Crypt": [],
    "PureJavaCrc32": [],
    "Crypt": [],
    "Sha2Crypt": [],
    "MessageDigestAlgorithms": [],
    "XXHash32": [],
    "UnixCrypt": [
        [
            "B64",
            "org.apache.commons.codec.digest.B64"
        ]
    ],
    "PureJavaCrc32C": [],
    "Blake3": [],
    "HmacUtils": [],
    "MurmurHash3": [
        [
            "StringUtils",
            "org.apache.commons.codec.binary.StringUtils"
        ]
    ],
    "B64": [],
    "HmacAlgorithms": [],
    "CharEncodingTest": [],
    "CharsetsTest": [],
    "StringEncoderComparatorTest": [],
    "EncoderExceptionTest": [],
    "BinaryEncoderAbstractTest": [],
    "DecoderExceptionTest": [],
    "StringEncoderAbstractTest": [],
    "PercentCodecTest": [],
    "QCodecTest": [],
    "QuotedPrintableCodecTest": [],
    "UtilsTest": [],
    "RFC1522CodecTest": [],
    "BCodecTest": [],
    "URLCodecTest": [],
    "BaseNTestData": [],
    "StringUtilsTest": [],
    "HexTest": [],
    "Base32InputStreamTest": [
        [
            "Base32TestData",
            "org.apache.commons.codec.binary.Base32TestData"
        ],
        [
            "BaseNTestData",
            "org.apache.commons.codec.binary.BaseNTestData"
        ],
        [
            "Codec105ErrorInputStream",
            "org.apache.commons.codec.binary.Codec105ErrorInputStream"
        ]
    ],
    "AllocateDirectHexTest": [
        [
            "HexTest",
            "org.apache.commons.codec.binary.HexTest"
        ]
    ],
    "Base64TestData": [],
    "Base32OutputStreamTest": [
        [
            "Base32Test",
            "org.apache.commons.codec.binary.Base32Test"
        ],
        [
            "Base32TestData",
            "org.apache.commons.codec.binary.Base32TestData"
        ],
        [
            "BaseNTestData",
            "org.apache.commons.codec.binary.BaseNTestData"
        ]
    ],
    "BinaryCodecTest": [],
    "Base64Test": [
        [
            "Base64TestData",
            "org.apache.commons.codec.binary.Base64TestData"
        ],
        [
            "BaseNCodecTest",
            "org.apache.commons.codec.binary.BaseNCodecTest"
        ],
        [
            "BaseNTestData",
            "org.apache.commons.codec.binary.BaseNTestData"
        ]
    ],
    "Base32Test": [
        [
            "BaseNTestData",
            "org.apache.commons.codec.binary.BaseNTestData"
        ]
    ],
    "Base16TestData": [],
    "Codec105ErrorInputStream": [],
    "CharSequenceUtilsTest": [],
    "Base64Codec13Test": [],
    "Base32TestData": [],
    "BaseNCodecTest": [],
    "Base64InputStreamTest": [
        [
            "Base64TestData",
            "org.apache.commons.codec.binary.Base64TestData"
        ],
        [
            "BaseNTestData",
            "org.apache.commons.codec.binary.BaseNTestData"
        ],
        [
            "Codec105ErrorInputStream",
            "org.apache.commons.codec.binary.Codec105ErrorInputStream"
        ]
    ],
    "Base16InputStreamTest": [
        [
            "BaseNTestData",
            "org.apache.commons.codec.binary.BaseNTestData"
        ]
    ],
    "Base64OutputStreamTest": [
        [
            "Base64Test",
            "org.apache.commons.codec.binary.Base64Test"
        ],
        [
            "Base64TestData",
            "org.apache.commons.codec.binary.Base64TestData"
        ],
        [
            "BaseNTestData",
            "org.apache.commons.codec.binary.BaseNTestData"
        ]
    ],
    "Base16Test": [
        [
            "Base16TestData",
            "org.apache.commons.codec.binary.Base16TestData"
        ],
        [
            "BaseNTestData",
            "org.apache.commons.codec.binary.BaseNTestData"
        ]
    ],
    "Base16OutputStreamTest": [
        [
            "BaseNTestData",
            "org.apache.commons.codec.binary.BaseNTestData"
        ]
    ],
    "RefinedSoundexTest": [
        [
            "StringEncoderAbstractTest",
            "org.apache.commons.codec.StringEncoderAbstractTest"
        ]
    ],
    "MatchRatingApproachEncoderTest": [
        [
            "StringEncoderAbstractTest",
            "org.apache.commons.codec.StringEncoderAbstractTest"
        ]
    ],
    "MetaphoneTest": [
        [
            "StringEncoderAbstractTest",
            "org.apache.commons.codec.StringEncoderAbstractTest"
        ]
    ],
    "DaitchMokotoffSoundexTest": [
        [
            "StringEncoderAbstractTest",
            "org.apache.commons.codec.StringEncoderAbstractTest"
        ]
    ],
    "Caverphone1Test": [
        [
            "StringEncoderAbstractTest",
            "org.apache.commons.codec.StringEncoderAbstractTest"
        ]
    ],
    "DoubleMetaphoneTest": [
        [
            "StringEncoderAbstractTest",
            "org.apache.commons.codec.StringEncoderAbstractTest"
        ]
    ],
    "ColognePhoneticTest": [
        [
            "StringEncoderAbstractTest",
            "org.apache.commons.codec.StringEncoderAbstractTest"
        ]
    ],
    "DoubleMetaphone2Test": [
        [
            "StringEncoderAbstractTest",
            "org.apache.commons.codec.StringEncoderAbstractTest"
        ]
    ],
    "NysiisTest": [
        [
            "StringEncoderAbstractTest",
            "org.apache.commons.codec.StringEncoderAbstractTest"
        ]
    ],
    "SoundexTest": [
        [
            "StringEncoderAbstractTest",
            "org.apache.commons.codec.StringEncoderAbstractTest"
        ]
    ],
    "Caverphone2Test": [
        [
            "StringEncoderAbstractTest",
            "org.apache.commons.codec.StringEncoderAbstractTest"
        ]
    ],
    "BeiderMorseEncoderTest": [
        [
            "StringEncoderAbstractTest",
            "org.apache.commons.codec.StringEncoderAbstractTest"
        ]
    ],
    "PhoneticEnginePerformanceTest": [],
    "CacheSubSequencePerformanceTest": [],
    "LanguageGuessingTest": [],
    "PhoneticEngineTest": [],
    "RuleTest": [],
    "PhoneticEngineRegressionTest": [],
    "B64Test": [],
    "Blake3TestVectorsTest": [],
    "Sha2CryptTest": [],
    "XXHash32OverflowTest": [],
    "MurmurHash2Test": [],
    "XXHash32Test": [],
    "Blake3Test": [],
    "PureJavaCrc32CTest": [],
    "MurmurHash3Test": [],
    "PureJavaCrc32Test": []
}