{
    "0": "MultiPrinterParser",
    "1": "MoneyPrinter",
    "2": "MoneyPrintContext",
    "3": "MoneyParser",
    "6": "MoneyFormatter",
    "7": "MoneyFormatException",
    "8": "CurrencyUnit",
    "9": "BigMoney",
    "10": "MoneyParseContext",
    "11": "MoneyAmountStyle",
    "12": "GroupingStyle",
    "13": "IllegalCurrencyException",
    "14": "SignedPrinterParser",
    "15": "LiteralPrinterParser",
    "16": "AmountPrinterParser",
    "17": "Money",
    "18": "BigMoneyProvider",
    "19": "MoneyFormatterBuilder",
    "20": "CurrencyMismatchException",
    "21": "MoneyUtils",
    "23": "TestMoneyFormatterException",
    "24": "TestMoneyFormatterBuilder",
    "25": "TestMoneyAmountStyle",
    "26": "TestMoneyFormatter",
    "27": "TestMoneyParseContext",
    "28": "TestMoney",
    "29": "TestMoneyUtils_Money",
    "30": "TestBigMoney",
    "31": "TestCurrencyUnitExtension",
    "32": "TestStringConvert",
    "33": "TestIllegalCurrencyException",
    "34": "TestCurrencyUnit",
    "35": "TestMoneyUtils_BigMoney",
    "36": "TestCurrencyMismatchException",
    "37": "CurrencyUnitDataProvider",
    "38": "Ser",
    "39": "DefaultCurrencyUnitDataProvider"
}